{
  "delivered_at": "2026-04-12T16:59:43+00:00",
  "delivery_path": "/Users/ywf/coding/arena-pretext-ui/.tasks/engineer-a/DELIVERY.md",
  "frontstage_disposition": null,
  "kind": "completion",
  "next_action": null,
  "notified_at": "2026-04-12T16:59:48+00:00",
  "notify_message": "ARENA-007 complete from engineer-a to engineer-b. Read /Users/ywf/coding/arena-pretext-ui/.tasks/engineer-a/DELIVERY.md and write a durable Consumed ACK when handled.",
  "source": "engineer-a",
  "target": "engineer-b",
  "task_id": "ARENA-007",
  "user_summary": null,
  "verdict": null
}
